aquiles/deploy_config.py
aquiles/main.py
aquiles/auth/__init__.py
aquiles/auth/jwt_aq.py
aquiles/auth/middleware.py
aquiles/cli/__init__.py
aquiles/cli/cli.py
aquiles/client/__init__.py
aquiles/client/asynclient.py
aquiles/client/client.py
aquiles/configs/__init__.py
aquiles/configs/configs.py
aquiles/connection/__init__.py
aquiles/connection/connection.py
aquiles/connection/qdrant.py
aquiles/mcp/__init__.py
aquiles/mcp/midd.py
aquiles/mcp/serve.py
aquiles/models/__init__.py
aquiles/models/models.py
aquiles/rerank/__init__.py
aquiles/rerank/api.py
aquiles/rerank/rerank.py
aquiles/schemas/__init__.py
aquiles/schemas/reds_sc.py
aquiles/static/add.png
aquiles/static/aq-fav.png
aquiles/static/aq-rag2.png
aquiles/static/config.png
aquiles/static/create.png
aquiles/static/playground.png
aquiles/static/query.png
aquiles/templates/login_ui.html
aquiles/templates/status.html
aquiles/templates/ui.html
aquiles/utils/__init__.py
aquiles/utils/rate_limit_manager.py
aquiles/utils/utils.py
aquiles/wrapper/__init__.py
aquiles/wrapper/basewrapper.py
aquiles/wrapper/postgres.py
aquiles/wrapper/qdrantwr.py
aquiles/wrapper/redswr.py
aquiles_rag-0.5.5.dist-info/licenses/LICENSE
aquiles_rag-0.5.5.dist-info/METADATA
aquiles_rag-0.5.5.dist-info/WHEEL
aquiles_rag-0.5.5.dist-info/entry_points.txt
aquiles_rag-0.5.5.dist-info/top_level.txt
aquiles_rag-0.5.5.dist-info/RECORD
