Metadata-Version: 2.4
Name: aquiles-rag
Version: 0.5.5
Summary: Aquiles-RAG is a high-performance Augmented Recovery-Generation (RAG) solution based on Redis, Qdrant or PostgreSQLRAG. It offers a high-level interface using FastAPI REST APIs.
Author-email: Aquiles-ai / Fredy <aquilesaicontact@gmail.com>
License: Apache License 2.0
Project-URL: Homepage, https://github.com/Aquiles-ai/Aquiles-RAG
Project-URL: Issues, https://github.com/Aquiles-ai/Aquiles-RAG/issues
Keywords: fastapi,ai,rag,vector-database
Classifier: Development Status :: 4 - Beta
Classifier: Programming Language :: Python :: 3
Classifier: Programming Language :: Python :: 3.8
Classifier: Programming Language :: Python :: 3.9
Classifier: Programming Language :: Python :: 3.10
Classifier: License :: OSI Approved :: Apache Software License
Classifier: Operating System :: OS Independent
Classifier: Environment :: Web Environment
Classifier: Topic :: Software Development :: Build Tools
Requires-Python: >=3.8
License-File: LICENSE
Requires-Dist: Werkzeug
Requires-Dist: Jinja2
Requires-Dist: passlib[bcrypt]
Requires-Dist: fastapi
Requires-Dist: uvicorn
Requires-Dist: psutil
Requires-Dist: pydantic
Requires-Dist: pydantic[email]
Requires-Dist: pydantic-settings
Requires-Dist: python-multipart
Requires-Dist: aiofiles
Requires-Dist: click>=8.0.0
Requires-Dist: platformdirs
Requires-Dist: redis[hiredis]
Requires-Dist: numpy
Requires-Dist: python-jose[cryptography]
Requires-Dist: bcrypt==4.0.1
Requires-Dist: PyJWT
Requires-Dist: qdrant-client
Requires-Dist: qdrant-client[fastembed]
Requires-Dist: rich
Requires-Dist: asyncpg
Requires-Dist: fastembed
Requires-Dist: fastembed-gpu
Requires-Dist: fastmcp
Provides-Extra: dev
Requires-Dist: pytest; extra == "dev"
Requires-Dist: black; extra == "dev"
Requires-Dist: isort; extra == "dev"
Requires-Dist: mypy; extra == "dev"
Dynamic: license-file
